aea_ledger_ethereum/__init__.py
aea_ledger_ethereum/ethereum.py
aea_ledger_ethereum-1.1.2.dist-info/LICENSE
aea_ledger_ethereum-1.1.2.dist-info/METADATA
aea_ledger_ethereum-1.1.2.dist-info/WHEEL
aea_ledger_ethereum-1.1.2.dist-info/entry_points.txt
aea_ledger_ethereum-1.1.2.dist-info/top_level.txt
aea_ledger_ethereum-1.1.2.dist-info/RECORD
